habmapslib/Appender.py
habmapslib/ConfHandler.py
habmapslib/GPSAppender.py
habmapslib/HMTail.py
habmapslib/HabMapsMessage.py
habmapslib/InitChecks.py
habmapslib/MapTracker.py
habmapslib/Parser.py
habmapslib/__init__.py
habmapslib/__main__.py
habmapslib/cli.py
habmapslib/confyaml.py
habmapslib-2.0.1.dist-info/LICENSE.txt
habmapslib-2.0.1.dist-info/METADATA
habmapslib-2.0.1.dist-info/WHEEL
habmapslib-2.0.1.dist-info/top_level.txt
habmapslib-2.0.1.dist-info/RECORD
