Metadata-Version: 2.1
Name: habmapslib
Version: 2.0.1
Summary: Librería para el acceso a habmaps
Home-page: https://github.com/alpeza/habmapsgateway
Author: Alpeza
Author-email: 
Project-URL: Bug Reports, https://github.com/alpeza/habmapsgateway/issues
Project-URL: Funding, https://github.com/alpeza/habmapsgateway/issues
Project-URL: Say Thanks!, https://github.com/alpeza/habmapsgateway/issues
Project-URL: Source, https://github.com/alpeza/habmapsgateway
Classifier: Intended Audience :: Developers
Classifier: License :: OSI Approved :: MIT License
Classifier: Operating System :: OS Independent
Classifier: Programming Language :: Python :: 3
Classifier: Programming Language :: Python :: 3.6
Classifier: Programming Language :: Python :: 3.7
Classifier: Programming Language :: Python :: 3.8
Classifier: Programming Language :: Python :: 3.9
Requires-Python: >=3.6, <4
License-File: LICENSE.txt
Requires-Dist: paho-mqtt (>=1.5.1)
Requires-Dist: click (>=7.1.2)
Requires-Dist: PyYAML (>=3.11)
